{
   "text": "In general the sediment units (fine detritus gyttja) become lighter coloured towards the surface of the sequence. There are, however, distinct changes in magnetic susceptibility within GU-3, which also contains a distinct layer of clastic sediment (approximately 1 mm thick) with high magnetic susceptibility at depth of 5.16 m. Magnetic susceptibility remains variable in GU-2, which is a lighter brown fine detritus gyttja. The onset of liming within the catchment causes GU-1 to be characterised by thin layers of light coloured non-dissolved calcium carbonate. The magnetic susceptibility of the freeze-core was not determined.",
   "entities": {
      "Token": [
         {
            "indices": [
               0,
               2
            ],
            "category": "IN",
            "kind": "prep",
            "id": 0,
            "head": 10
         },
         {
            "indices": [
               3,
               10
            ],
            "category": "JJ",
            "kind": "amod",
            "id": 1,
            "head": 0
         },
         {
            "indices": [
               11,
               14
            ],
            "category": "DT",
            "kind": "det",
            "id": 2,
            "head": 4
         },
         {
            "indices": [
               15,
               23
            ],
            "category": "NN",
            "kind": "compound",
            "id": 3,
            "head": 4
         },
         {
            "indices": [
               24,
               29
            ],
            "category": "NNS",
            "kind": "nsubj",
            "id": 4,
            "head": 10
         },
         {
            "indices": [
               30,
               31
            ],
            "category": "-LRB-",
            "kind": "punct",
            "id": 5,
            "head": 4
         },
         {
            "indices": [
               31,
               35
            ],
            "category": "JJ",
            "kind": "amod",
            "id": 6,
            "head": 7
         },
         {
            "indices": [
               36,
               44
            ],
            "category": "NN",
            "kind": "compound",
            "id": 7,
            "head": 8
         },
         {
            "indices": [
               45,
               51
            ],
            "category": "NN",
            "kind": "appos",
            "id": 8,
            "head": 4
         },
         {
            "indices": [
               51,
               52
            ],
            "category": "-RRB-",
            "kind": "punct",
            "id": 9,
            "head": 4
         },
         {
            "indices": [
               53,
               59
            ],
            "category": "VBP",
            "kind": "ROOT",
            "id": 10,
            "head": 10
         },
         {
            "indices": [
               60,
               67
            ],
            "category": "JJR",
            "kind": "amod",
            "id": 11,
            "head": 12
         },
         {
            "indices": [
               68,
               76
            ],
            "category": "JJ",
            "kind": "attr",
            "id": 12,
            "head": 10
         },
         {
            "indices": [
               77,
               84
            ],
            "category": "IN",
            "kind": "prep",
            "id": 13,
            "head": 12
         },
         {
            "indices": [
               85,
               88
            ],
            "category": "DT",
            "kind": "det",
            "id": 14,
            "head": 15
         },
         {
            "indices": [
               89,
               96
            ],
            "category": "NN",
            "kind": "pobj",
            "id": 15,
            "head": 13
         },
         {
            "indices": [
               97,
               99
            ],
            "category": "IN",
            "kind": "prep",
            "id": 16,
            "head": 15
         },
         {
            "indices": [
               100,
               103
            ],
            "category": "DT",
            "kind": "det",
            "id": 17,
            "head": 18
         },
         {
            "indices": [
               104,
               112
            ],
            "category": "NN",
            "kind": "pobj",
            "id": 18,
            "head": 16
         },
         {
            "indices": [
               112,
               113
            ],
            "category": ".",
            "kind": "punct",
            "id": 19,
            "head": 10
         },
         {
            "indices": [
               114,
               119
            ],
            "category": "EX",
            "kind": "expl",
            "id": 20,
            "head": 21
         },
         {
            "indices": [
               120,
               123
            ],
            "category": "VBP",
            "kind": "ROOT",
            "id": 21,
            "head": 21
         },
         {
            "indices": [
               123,
               124
            ],
            "category": ",",
            "kind": "punct",
            "id": 22,
            "head": 21
         },
         {
            "indices": [
               125,
               132
            ],
            "category": "RB",
            "kind": "advmod",
            "id": 23,
            "head": 21
         },
         {
            "indices": [
               132,
               133
            ],
            "category": ",",
            "kind": "punct",
            "id": 24,
            "head": 21
         },
         {
            "indices": [
               134,
               142
            ],
            "category": "JJ",
            "kind": "amod",
            "id": 25,
            "head": 26
         },
         {
            "indices": [
               143,
               150
            ],
            "category": "NNS",
            "kind": "nsubj",
            "id": 26,
            "head": 59
         },
         {
            "indices": [
               151,
               153
            ],
            "category": "IN",
            "kind": "prep",
            "id": 27,
            "head": 26
         },
         {
            "indices": [
               154,
               162
            ],
            "category": "JJ",
            "kind": "amod",
            "id": 28,
            "head": 29
         },
         {
            "indices": [
               163,
               177
            ],
            "category": "NN",
            "kind": "pobj",
            "id": 29,
            "head": 27
         },
         {
            "indices": [
               178,
               184
            ],
            "category": "IN",
            "kind": "prep",
            "id": 30,
            "head": 26
         },
         {
            "indices": [
               185,
               189
            ],
            "category": "NN",
            "kind": "pobj",
            "id": 31,
            "head": 30
         },
         {
            "indices": [
               189,
               190
            ],
            "category": ",",
            "kind": "punct",
            "id": 32,
            "head": 26
         },
         {
            "indices": [
               191,
               196
            ],
            "category": "WDT",
            "kind": "nsubj",
            "id": 33,
            "head": 35
         },
         {
            "indices": [
               197,
               201
            ],
            "category": "RB",
            "kind": "advmod",
            "id": 34,
            "head": 35
         },
         {
            "indices": [
               202,
               210
            ],
            "category": "VBZ",
            "kind": "relcl",
            "id": 35,
            "head": 26
         },
         {
            "indices": [
               211,
               212
            ],
            "category": "DT",
            "kind": "det",
            "id": 36,
            "head": 38
         },
         {
            "indices": [
               213,
               221
            ],
            "category": "JJ",
            "kind": "amod",
            "id": 37,
            "head": 38
         },
         {
            "indices": [
               222,
               227
            ],
            "category": "NN",
            "kind": "dobj",
            "id": 38,
            "head": 35
         },
         {
            "indices": [
               228,
               230
            ],
            "category": "IN",
            "kind": "prep",
            "id": 39,
            "head": 38
         },
         {
            "indices": [
               231,
               238
            ],
            "category": "JJ",
            "kind": "amod",
            "id": 40,
            "head": 41
         },
         {
            "indices": [
               239,
               247
            ],
            "category": "NN",
            "kind": "pobj",
            "id": 41,
            "head": 39
         },
         {
            "indices": [
               248,
               249
            ],
            "category": "-LRB-",
            "kind": "punct",
            "id": 42,
            "head": 41
         },
         {
            "indices": [
               249,
               262
            ],
            "category": "RB",
            "kind": "advmod",
            "id": 43,
            "head": 44
         },
         {
            "indices": [
               263,
               264
            ],
            "category": "CD",
            "kind": "nummod",
            "id": 44,
            "head": 45
         },
         {
            "indices": [
               265,
               267
            ],
            "category": "NN",
            "kind": "npadvmod",
            "id": 45,
            "head": 46
         },
         {
            "indices": [
               268,
               273
            ],
            "category": "JJ",
            "kind": "amod",
            "id": 46,
            "head": 41
         },
         {
            "indices": [
               273,
               274
            ],
            "category": "-RRB-",
            "kind": "punct",
            "id": 47,
            "head": 41
         },
         {
            "indices": [
               275,
               279
            ],
            "category": "IN",
            "kind": "prep",
            "id": 48,
            "head": 38
         },
         {
            "indices": [
               280,
               284
            ],
            "category": "JJ",
            "kind": "amod",
            "id": 49,
            "head": 51
         },
         {
            "indices": [
               285,
               293
            ],
            "category": "JJ",
            "kind": "amod",
            "id": 50,
            "head": 51
         },
         {
            "indices": [
               294,
               308
            ],
            "category": "NN",
            "kind": "pobj",
            "id": 51,
            "head": 48
         },
         {
            "indices": [
               309,
               311
            ],
            "category": "IN",
            "kind": "prep",
            "id": 52,
            "head": 51
         },
         {
            "indices": [
               312,
               317
            ],
            "category": "NN",
            "kind": "pobj",
            "id": 53,
            "head": 52
         },
         {
            "indices": [
               318,
               320
            ],
            "category": "IN",
            "kind": "prep",
            "id": 54,
            "head": 53
         },
         {
            "indices": [
               321,
               325
            ],
            "category": "CD",
            "kind": "nummod",
            "id": 55,
            "head": 58
         },
         {
            "indices": [
               326,
               328
            ],
            "category": "NN",
            "kind": "compound",
            "id": 56,
            "head": 57
         },
         {
            "indices": [
               329,
               337
            ],
            "category": "JJ",
            "kind": "compound",
            "id": 57,
            "head": 58
         },
         {
            "indices": [
               338,
               352
            ],
            "category": "NN",
            "kind": "pobj",
            "id": 58,
            "head": 54
         },
         {
            "indices": [
               353,
               360
            ],
            "category": "VBZ",
            "kind": "conj",
            "id": 59,
            "head": 21
         },
         {
            "indices": [
               361,
               369
            ],
            "category": "JJ",
            "kind": "acomp",
            "id": 60,
            "head": 59
         },
         {
            "indices": [
               370,
               372
            ],
            "category": "IN",
            "kind": "prep",
            "id": 61,
            "head": 59
         },
         {
            "indices": [
               373,
               377
            ],
            "category": "NNP",
            "kind": "dep",
            "id": 62,
            "head": 63
         },
         {
            "indices": [
               377,
               378
            ],
            "category": ",",
            "kind": "punct",
            "id": 63,
            "head": 59
         },
         {
            "indices": [
               379,
               384
            ],
            "category": "WDT",
            "kind": "nsubj",
            "id": 64,
            "head": 65
         },
         {
            "indices": [
               385,
               387
            ],
            "category": "VBZ",
            "kind": "relcl",
            "id": 65,
            "head": 59
         },
         {
            "indices": [
               388,
               389
            ],
            "category": "DT",
            "kind": "det",
            "id": 66,
            "head": 70
         },
         {
            "indices": [
               390,
               397
            ],
            "category": "JJR",
            "kind": "amod",
            "id": 67,
            "head": 70
         },
         {
            "indices": [
               398,
               403
            ],
            "category": "JJ",
            "kind": "amod",
            "id": 68,
            "head": 70
         },
         {
            "indices": [
               404,
               408
            ],
            "category": "JJ",
            "kind": "amod",
            "id": 69,
            "head": 70
         },
         {
            "indices": [
               409,
               417
            ],
            "category": "NN",
            "kind": "compound",
            "id": 70,
            "head": 71
         },
         {
            "indices": [
               418,
               424
            ],
            "category": "NN",
            "kind": "attr",
            "id": 71,
            "head": 65
         },
         {
            "indices": [
               424,
               425
            ],
            "category": ".",
            "kind": "punct",
            "id": 72,
            "head": 59
         },
         {
            "indices": [
               426,
               429
            ],
            "category": "DT",
            "kind": "det",
            "id": 73,
            "head": 74
         },
         {
            "indices": [
               430,
               435
            ],
            "category": "NN",
            "kind": "nsubj",
            "id": 74,
            "head": 80
         },
         {
            "indices": [
               436,
               438
            ],
            "category": "IN",
            "kind": "prep",
            "id": 75,
            "head": 74
         },
         {
            "indices": [
               439,
               445
            ],
            "category": "NN",
            "kind": "pobj",
            "id": 76,
            "head": 75
         },
         {
            "indices": [
               446,
               452
            ],
            "category": "IN",
            "kind": "prep",
            "id": 77,
            "head": 76
         },
         {
            "indices": [
               453,
               456
            ],
            "category": "DT",
            "kind": "det",
            "id": 78,
            "head": 79
         },
         {
            "indices": [
               457,
               466
            ],
            "category": "NN",
            "kind": "pobj",
            "id": 79,
            "head": 77
         },
         {
            "indices": [
               467,
               473
            ],
            "category": "VBZ",
            "kind": "ROOT",
            "id": 80,
            "head": 80
         },
         {
            "indices": [
               474,
               478
            ],
            "category": "NNP",
            "kind": "dep",
            "id": 81,
            "head": 84
         },
         {
            "indices": [
               479,
               481
            ],
            "category": "TO",
            "kind": "aux",
            "id": 82,
            "head": 84
         },
         {
            "indices": [
               482,
               484
            ],
            "category": "VB",
            "kind": "auxpass",
            "id": 83,
            "head": 84
         },
         {
            "indices": [
               485,
               498
            ],
            "category": "VBN",
            "kind": "xcomp",
            "id": 84,
            "head": 80
         },
         {
            "indices": [
               499,
               501
            ],
            "category": "IN",
            "kind": "agent",
            "id": 85,
            "head": 84
         },
         {
            "indices": [
               502,
               506
            ],
            "category": "JJ",
            "kind": "amod",
            "id": 86,
            "head": 87
         },
         {
            "indices": [
               507,
               513
            ],
            "category": "NNS",
            "kind": "pobj",
            "id": 87,
            "head": 85
         },
         {
            "indices": [
               514,
               516
            ],
            "category": "IN",
            "kind": "prep",
            "id": 88,
            "head": 87
         },
         {
            "indices": [
               517,
               522
            ],
            "category": "JJ",
            "kind": "amod",
            "id": 89,
            "head": 95
         },
         {
            "indices": [
               523,
               531
            ],
            "category": "JJ",
            "kind": "amod",
            "id": 90,
            "head": 95
         },
         {
            "indices": [
               532,
               535
            ],
            "category": "JJ",
            "kind": "dep",
            "id": 91,
            "head": 92
         },
         {
            "indices": [
               535,
               536
            ],
            "category": "JJ",
            "kind": "dep",
            "id": 92,
            "head": 93
         },
         {
            "indices": [
               536,
               545
            ],
            "category": "JJ",
            "kind": "amod",
            "id": 93,
            "head": 94
         },
         {
            "indices": [
               546,
               553
            ],
            "category": "NN",
            "kind": "compound",
            "id": 94,
            "head": 95
         },
         {
            "indices": [
               554,
               563
            ],
            "category": "NN",
            "kind": "pobj",
            "id": 95,
            "head": 88
         },
         {
            "indices": [
               563,
               564
            ],
            "category": ".",
            "kind": "punct",
            "id": 96,
            "head": 80
         },
         {
            "indices": [
               565,
               568
            ],
            "category": "DT",
            "kind": "det",
            "id": 97,
            "head": 99
         },
         {
            "indices": [
               569,
               577
            ],
            "category": "JJ",
            "kind": "amod",
            "id": 98,
            "head": 99
         },
         {
            "indices": [
               578,
               592
            ],
            "category": "NN",
            "kind": "nsubjpass",
            "id": 99,
            "head": 107
         },
         {
            "indices": [
               593,
               595
            ],
            "category": "IN",
            "kind": "prep",
            "id": 100,
            "head": 99
         },
         {
            "indices": [
               596,
               599
            ],
            "category": "DT",
            "kind": "det",
            "id": 101,
            "head": 104
         },
         {
            "indices": [
               600,
               606
            ],
            "category": "NN",
            "kind": "compound",
            "id": 102,
            "head": 104
         },
         {
            "indices": [
               606,
               607
            ],
            "category": "HYPH",
            "kind": "punct",
            "id": 103,
            "head": 104
         },
         {
            "indices": [
               607,
               611
            ],
            "category": "NN",
            "kind": "pobj",
            "id": 104,
            "head": 100
         },
         {
            "indices": [
               612,
               615
            ],
            "category": "VBD",
            "kind": "auxpass",
            "id": 105,
            "head": 107
         },
         {
            "indices": [
               616,
               619
            ],
            "category": "RB",
            "kind": "neg",
            "id": 106,
            "head": 107
         },
         {
            "indices": [
               620,
               630
            ],
            "category": "VBN",
            "kind": "ROOT",
            "id": 107,
            "head": 107
         },
         {
            "indices": [
               630,
               631
            ],
            "category": ".",
            "kind": "punct",
            "id": 108,
            "head": 107
         }
      ],
      "ORG": [
         {
            "indices": [
               185,
               189
            ]
         },
         {
            "indices": [
               373,
               377
            ]
         }
      ],
      "QUANTITY": [
         {
            "indices": [
               249,
               267
            ]
         }
      ],
      "CARDINAL": [
         {
            "indices": [
               321,
               325
            ]
         }
      ],
      "NickDependency": [
         {
            "args": [
               "become",
               "In"
            ],
            "kind": "prep",
            "indices": [
               0,
               59
            ]
         },
         {
            "args": [
               "In",
               "general"
            ],
            "kind": "amod",
            "indices": [
               0,
               10
            ]
         },
         {
            "args": [
               "units",
               "the"
            ],
            "kind": "det",
            "indices": [
               11,
               29
            ]
         },
         {
            "args": [
               "units",
               "sediment"
            ],
            "kind": "compound",
            "indices": [
               15,
               29
            ]
         },
         {
            "args": [
               "become",
               "units"
            ],
            "kind": "nsubj",
            "indices": [
               24,
               59
            ]
         },
         {
            "args": [
               "units",
               "("
            ],
            "kind": "punct",
            "indices": [
               24,
               31
            ]
         },
         {
            "args": [
               "detritus",
               "fine"
            ],
            "kind": "amod",
            "indices": [
               31,
               44
            ]
         },
         {
            "args": [
               "gyttja",
               "detritus"
            ],
            "kind": "compound",
            "indices": [
               36,
               51
            ]
         },
         {
            "args": [
               "units",
               "gyttja"
            ],
            "kind": "appos",
            "indices": [
               24,
               51
            ]
         },
         {
            "args": [
               "units",
               ")"
            ],
            "kind": "punct",
            "indices": [
               24,
               52
            ]
         },
         {
            "args": [
               "become",
               "become"
            ],
            "kind": "ROOT",
            "indices": [
               53,
               59
            ]
         },
         {
            "args": [
               "coloured",
               "lighter"
            ],
            "kind": "amod",
            "indices": [
               60,
               76
            ]
         },
         {
            "args": [
               "become",
               "coloured"
            ],
            "kind": "attr",
            "indices": [
               53,
               76
            ]
         },
         {
            "args": [
               "coloured",
               "towards"
            ],
            "kind": "prep",
            "indices": [
               68,
               84
            ]
         },
         {
            "args": [
               "surface",
               "the"
            ],
            "kind": "det",
            "indices": [
               85,
               96
            ]
         },
         {
            "args": [
               "towards",
               "surface"
            ],
            "kind": "pobj",
            "indices": [
               77,
               96
            ]
         },
         {
            "args": [
               "surface",
               "of"
            ],
            "kind": "prep",
            "indices": [
               89,
               99
            ]
         },
         {
            "args": [
               "sequence",
               "the"
            ],
            "kind": "det",
            "indices": [
               100,
               112
            ]
         },
         {
            "args": [
               "of",
               "sequence"
            ],
            "kind": "pobj",
            "indices": [
               97,
               112
            ]
         },
         {
            "args": [
               "become",
               "."
            ],
            "kind": "punct",
            "indices": [
               53,
               113
            ]
         },
         {
            "args": [
               "are",
               "There"
            ],
            "kind": "expl",
            "indices": [
               114,
               123
            ]
         },
         {
            "args": [
               "are",
               "are"
            ],
            "kind": "ROOT",
            "indices": [
               120,
               123
            ]
         },
         {
            "args": [
               "are",
               ","
            ],
            "kind": "punct",
            "indices": [
               120,
               124
            ]
         },
         {
            "args": [
               "are",
               "however"
            ],
            "kind": "advmod",
            "indices": [
               120,
               132
            ]
         },
         {
            "args": [
               "are",
               ","
            ],
            "kind": "punct",
            "indices": [
               120,
               133
            ]
         },
         {
            "args": [
               "changes",
               "distinct"
            ],
            "kind": "amod",
            "indices": [
               134,
               150
            ]
         },
         {
            "args": [
               "remains",
               "changes"
            ],
            "kind": "nsubj",
            "indices": [
               143,
               360
            ]
         },
         {
            "args": [
               "changes",
               "in"
            ],
            "kind": "prep",
            "indices": [
               143,
               153
            ]
         },
         {
            "args": [
               "susceptibility",
               "magnetic"
            ],
            "kind": "amod",
            "indices": [
               154,
               177
            ]
         },
         {
            "args": [
               "in",
               "susceptibility"
            ],
            "kind": "pobj",
            "indices": [
               151,
               177
            ]
         },
         {
            "args": [
               "changes",
               "within"
            ],
            "kind": "prep",
            "indices": [
               143,
               184
            ]
         },
         {
            "args": [
               "within",
               "GU-3"
            ],
            "kind": "pobj",
            "indices": [
               178,
               189
            ]
         },
         {
            "args": [
               "changes",
               ","
            ],
            "kind": "punct",
            "indices": [
               143,
               190
            ]
         },
         {
            "args": [
               "contains",
               "which"
            ],
            "kind": "nsubj",
            "indices": [
               191,
               210
            ]
         },
         {
            "args": [
               "contains",
               "also"
            ],
            "kind": "advmod",
            "indices": [
               197,
               210
            ]
         },
         {
            "args": [
               "changes",
               "contains"
            ],
            "kind": "relcl",
            "indices": [
               143,
               210
            ]
         },
         {
            "args": [
               "layer",
               "a"
            ],
            "kind": "det",
            "indices": [
               211,
               227
            ]
         },
         {
            "args": [
               "layer",
               "distinct"
            ],
            "kind": "amod",
            "indices": [
               213,
               227
            ]
         },
         {
            "args": [
               "contains",
               "layer"
            ],
            "kind": "dobj",
            "indices": [
               202,
               227
            ]
         },
         {
            "args": [
               "layer",
               "of"
            ],
            "kind": "prep",
            "indices": [
               222,
               230
            ]
         },
         {
            "args": [
               "sediment",
               "clastic"
            ],
            "kind": "amod",
            "indices": [
               231,
               247
            ]
         },
         {
            "args": [
               "of",
               "sediment"
            ],
            "kind": "pobj",
            "indices": [
               228,
               247
            ]
         },
         {
            "args": [
               "sediment",
               "("
            ],
            "kind": "punct",
            "indices": [
               239,
               249
            ]
         },
         {
            "args": [
               "1",
               "approximately"
            ],
            "kind": "advmod",
            "indices": [
               249,
               264
            ]
         },
         {
            "args": [
               "mm",
               "1"
            ],
            "kind": "nummod",
            "indices": [
               263,
               267
            ]
         },
         {
            "args": [
               "thick",
               "mm"
            ],
            "kind": "npadvmod",
            "indices": [
               265,
               273
            ]
         },
         {
            "args": [
               "sediment",
               "thick"
            ],
            "kind": "amod",
            "indices": [
               239,
               273
            ]
         },
         {
            "args": [
               "sediment",
               ")"
            ],
            "kind": "punct",
            "indices": [
               239,
               274
            ]
         },
         {
            "args": [
               "layer",
               "with"
            ],
            "kind": "prep",
            "indices": [
               222,
               279
            ]
         },
         {
            "args": [
               "susceptibility",
               "high"
            ],
            "kind": "amod",
            "indices": [
               280,
               308
            ]
         },
         {
            "args": [
               "susceptibility",
               "magnetic"
            ],
            "kind": "amod",
            "indices": [
               285,
               308
            ]
         },
         {
            "args": [
               "with",
               "susceptibility"
            ],
            "kind": "pobj",
            "indices": [
               275,
               308
            ]
         },
         {
            "args": [
               "susceptibility",
               "at"
            ],
            "kind": "prep",
            "indices": [
               294,
               311
            ]
         },
         {
            "args": [
               "at",
               "depth"
            ],
            "kind": "pobj",
            "indices": [
               309,
               317
            ]
         },
         {
            "args": [
               "depth",
               "of"
            ],
            "kind": "prep",
            "indices": [
               312,
               320
            ]
         },
         {
            "args": [
               "susceptibility",
               "5.16"
            ],
            "kind": "nummod",
            "indices": [
               321,
               352
            ]
         },
         {
            "args": [
               "Magnetic",
               "m."
            ],
            "kind": "compound",
            "indices": [
               326,
               337
            ]
         },
         {
            "args": [
               "susceptibility",
               "Magnetic"
            ],
            "kind": "compound",
            "indices": [
               329,
               352
            ]
         },
         {
            "args": [
               "of",
               "susceptibility"
            ],
            "kind": "pobj",
            "indices": [
               318,
               352
            ]
         },
         {
            "args": [
               "are",
               "remains"
            ],
            "kind": "conj",
            "indices": [
               120,
               360
            ]
         },
         {
            "args": [
               "remains",
               "variable"
            ],
            "kind": "acomp",
            "indices": [
               353,
               369
            ]
         },
         {
            "args": [
               "remains",
               "in"
            ],
            "kind": "prep",
            "indices": [
               353,
               372
            ]
         },
         {
            "args": [
               ",",
               "GU-2"
            ],
            "kind": "dep",
            "indices": [
               373,
               378
            ]
         },
         {
            "args": [
               "remains",
               ","
            ],
            "kind": "punct",
            "indices": [
               353,
               378
            ]
         },
         {
            "args": [
               "is",
               "which"
            ],
            "kind": "nsubj",
            "indices": [
               379,
               387
            ]
         },
         {
            "args": [
               "remains",
               "is"
            ],
            "kind": "relcl",
            "indices": [
               353,
               387
            ]
         },
         {
            "args": [
               "detritus",
               "a"
            ],
            "kind": "det",
            "indices": [
               388,
               417
            ]
         },
         {
            "args": [
               "detritus",
               "lighter"
            ],
            "kind": "amod",
            "indices": [
               390,
               417
            ]
         },
         {
            "args": [
               "detritus",
               "brown"
            ],
            "kind": "amod",
            "indices": [
               398,
               417
            ]
         },
         {
            "args": [
               "detritus",
               "fine"
            ],
            "kind": "amod",
            "indices": [
               404,
               417
            ]
         },
         {
            "args": [
               "gyttja",
               "detritus"
            ],
            "kind": "compound",
            "indices": [
               409,
               424
            ]
         },
         {
            "args": [
               "is",
               "gyttja"
            ],
            "kind": "attr",
            "indices": [
               385,
               424
            ]
         },
         {
            "args": [
               "remains",
               "."
            ],
            "kind": "punct",
            "indices": [
               353,
               425
            ]
         },
         {
            "args": [
               "onset",
               "The"
            ],
            "kind": "det",
            "indices": [
               426,
               435
            ]
         },
         {
            "args": [
               "causes",
               "onset"
            ],
            "kind": "nsubj",
            "indices": [
               430,
               473
            ]
         },
         {
            "args": [
               "onset",
               "of"
            ],
            "kind": "prep",
            "indices": [
               430,
               438
            ]
         },
         {
            "args": [
               "of",
               "liming"
            ],
            "kind": "pobj",
            "indices": [
               436,
               445
            ]
         },
         {
            "args": [
               "liming",
               "within"
            ],
            "kind": "prep",
            "indices": [
               439,
               452
            ]
         },
         {
            "args": [
               "catchment",
               "the"
            ],
            "kind": "det",
            "indices": [
               453,
               466
            ]
         },
         {
            "args": [
               "within",
               "catchment"
            ],
            "kind": "pobj",
            "indices": [
               446,
               466
            ]
         },
         {
            "args": [
               "causes",
               "causes"
            ],
            "kind": "ROOT",
            "indices": [
               467,
               473
            ]
         },
         {
            "args": [
               "characterised",
               "GU-1"
            ],
            "kind": "dep",
            "indices": [
               474,
               498
            ]
         },
         {
            "args": [
               "characterised",
               "to"
            ],
            "kind": "aux",
            "indices": [
               479,
               498
            ]
         },
         {
            "args": [
               "characterised",
               "be"
            ],
            "kind": "auxpass",
            "indices": [
               482,
               498
            ]
         },
         {
            "args": [
               "causes",
               "characterised"
            ],
            "kind": "xcomp",
            "indices": [
               467,
               498
            ]
         },
         {
            "args": [
               "characterised",
               "by"
            ],
            "kind": "agent",
            "indices": [
               485,
               501
            ]
         },
         {
            "args": [
               "layers",
               "thin"
            ],
            "kind": "amod",
            "indices": [
               502,
               513
            ]
         },
         {
            "args": [
               "by",
               "layers"
            ],
            "kind": "pobj",
            "indices": [
               499,
               513
            ]
         },
         {
            "args": [
               "layers",
               "of"
            ],
            "kind": "prep",
            "indices": [
               507,
               516
            ]
         },
         {
            "args": [
               "carbonate",
               "light"
            ],
            "kind": "amod",
            "indices": [
               517,
               563
            ]
         },
         {
            "args": [
               "carbonate",
               "coloured"
            ],
            "kind": "amod",
            "indices": [
               523,
               563
            ]
         },
         {
            "args": [
               "-",
               "non"
            ],
            "kind": "dep",
            "indices": [
               532,
               536
            ]
         },
         {
            "args": [
               "dissolved",
               "-"
            ],
            "kind": "dep",
            "indices": [
               535,
               545
            ]
         },
         {
            "args": [
               "calcium",
               "dissolved"
            ],
            "kind": "amod",
            "indices": [
               536,
               553
            ]
         },
         {
            "args": [
               "carbonate",
               "calcium"
            ],
            "kind": "compound",
            "indices": [
               546,
               563
            ]
         },
         {
            "args": [
               "of",
               "carbonate"
            ],
            "kind": "pobj",
            "indices": [
               514,
               563
            ]
         },
         {
            "args": [
               "causes",
               "."
            ],
            "kind": "punct",
            "indices": [
               467,
               564
            ]
         },
         {
            "args": [
               "susceptibility",
               "The"
            ],
            "kind": "det",
            "indices": [
               565,
               592
            ]
         },
         {
            "args": [
               "susceptibility",
               "magnetic"
            ],
            "kind": "amod",
            "indices": [
               569,
               592
            ]
         },
         {
            "args": [
               "determined",
               "susceptibility"
            ],
            "kind": "nsubjpass",
            "indices": [
               578,
               630
            ]
         },
         {
            "args": [
               "susceptibility",
               "of"
            ],
            "kind": "prep",
            "indices": [
               578,
               595
            ]
         },
         {
            "args": [
               "core",
               "the"
            ],
            "kind": "det",
            "indices": [
               596,
               611
            ]
         },
         {
            "args": [
               "core",
               "freeze"
            ],
            "kind": "compound",
            "indices": [
               600,
               611
            ]
         },
         {
            "args": [
               "core",
               "-"
            ],
            "kind": "punct",
            "indices": [
               606,
               611
            ]
         },
         {
            "args": [
               "of",
               "core"
            ],
            "kind": "pobj",
            "indices": [
               593,
               611
            ]
         },
         {
            "args": [
               "determined",
               "was"
            ],
            "kind": "auxpass",
            "indices": [
               612,
               630
            ]
         },
         {
            "args": [
               "determined",
               "not"
            ],
            "kind": "neg",
            "indices": [
               616,
               630
            ]
         },
         {
            "args": [
               "determined",
               "determined"
            ],
            "kind": "ROOT",
            "indices": [
               620,
               630
            ]
         },
         {
            "args": [
               "determined",
               "."
            ],
            "kind": "punct",
            "indices": [
               620,
               631
            ]
         }
      ],
      "sentence": [
         {
            "indices": [
               0,
               113
            ]
         },
         {
            "indices": [
               114,
               425
            ]
         },
         {
            "indices": [
               426,
               564
            ]
         },
         {
            "indices": [
               565,
               631
            ]
         }
      ],
      "MEval-Quantity": [
         {
            "indices": [
               249,
               267
            ],
            "annotSet": 1,
            "annotId": "T1-1",
            "text": "approximately 1 mm",
            "other": "{\"mods\": [\"IsApproximate\"], \"unit\": \"mm\"}"
         },
         {
            "indices": [
               321,
               328
            ],
            "annotSet": 2,
            "annotId": "T1-2",
            "text": "5.16 m.",
            "other": "{\"unit\": \"m\"}"
         }
      ],
      "MEval-MeasuredProperty": [
         {
            "indices": [
               268,
               273
            ],
            "annotSet": 1,
            "annotId": "T4-1",
            "text": "thick",
            "other": "{\"HasQuantity\": \"T1-1\"}"
         },
         {
            "indices": [
               312,
               317
            ],
            "annotSet": 2,
            "annotId": "T2-2",
            "text": "depth",
            "other": "{\"HasQuantity\": \"T1-2\"}"
         }
      ],
      "MEval-MeasuredEntity": [
         {
            "indices": [
               213,
               247
            ],
            "annotSet": 1,
            "annotId": "T3-1",
            "text": "distinct layer of clastic sediment",
            "other": "{\"HasProperty\": \"T4-1\"}"
         },
         {
            "indices": [
               213,
               247
            ],
            "annotSet": 2,
            "annotId": "T5-2",
            "text": "distinct layer of clastic sediment",
            "other": "{\"HasProperty\": \"T2-2\"}"
         }
      ],
      "MEval-Qualifier": [
         {
            "indices": [
               280,
               308
            ],
            "annotSet": 2,
            "annotId": "T4-2",
            "text": "high magnetic susceptibility",
            "other": "{\"Qualifies\": \"T5-2\"}"
         }
      ],
      "h0Number": [
         {
            "indices": [
               249,
               262
            ],
            "text": "approximately"
         },
         {
            "indices": [
               263,
               264
            ],
            "text": "1"
         },
         {
            "indices": [
               265,
               267
            ],
            "text": "mm"
         },
         {
            "indices": [
               321,
               325
            ],
            "text": "5.16"
         }
      ],
      "h0Unit": [
         {
            "indices": [
               263,
               264
            ],
            "text": "1"
         },
         {
            "indices": [
               265,
               267
            ],
            "text": "mm"
         },
         {
            "indices": [
               268,
               273
            ],
            "text": "thick"
         },
         {
            "indices": [
               338,
               352
            ],
            "text": "susceptibility"
         }
      ],
      "h0MeasuredEntity": [
         {
            "indices": [
               265,
               267
            ],
            "text": "mm"
         },
         {
            "indices": [
               268,
               273
            ],
            "text": "thick"
         },
         {
            "indices": [
               239,
               247
            ],
            "text": "sediment"
         },
         {
            "indices": [
               312,
               317
            ],
            "text": "depth"
         }
      ],
      "h0NumberTP": [
         {
            "indices": [
               249,
               262
            ],
            "text": "approximately"
         }
      ],
      "h0UnitTP": [
         {
            "indices": [
               263,
               264
            ],
            "text": "1"
         }
      ]
   }
}