{
   "text": "In each sub-figures (a)\u2013(f) of Fig. 4, the x-coordinate pertains to the ratio of the number of the inserted objects and original data, while the y-coordinate concerns the computational time. According to the experimental results as shown in Table 9 and Fig. 4, we find that the computational time of both static (Algorithm 1) and incremental (Algorithm 3) algorithms are increasing monotonically along with the increasing of insert ratios. It is easy to get the incremental algorithm is always faster than the static algorithm when the inserting ratio increases from 10% to 100% according to Fig. 4(a)\u2013(e). In Fig. 4(f), we find the incremental algorithm is mush faster than the static algorithm when the inserting ratio is less than 85%, but slower than the static algorithm when the inserting ratio is more than 85%.",
   "entities": {
      "Token": [
         {
            "indices": [
               0,
               2
            ],
            "category": "IN",
            "kind": "ROOT",
            "id": 0,
            "head": 0
         },
         {
            "indices": [
               3,
               7
            ],
            "category": "DT",
            "kind": "det",
            "id": 1,
            "head": 4
         },
         {
            "indices": [
               8,
               11
            ],
            "category": "NN",
            "kind": "dep",
            "id": 2,
            "head": 3
         },
         {
            "indices": [
               11,
               12
            ],
            "category": "NNS",
            "kind": "dep",
            "id": 3,
            "head": 4
         },
         {
            "indices": [
               12,
               19
            ],
            "category": "NNS",
            "kind": "pobj",
            "id": 4,
            "head": 0
         },
         {
            "indices": [
               20,
               21
            ],
            "category": "-LRB-",
            "kind": "punct",
            "id": 5,
            "head": 6
         },
         {
            "indices": [
               21,
               26
            ],
            "category": "NNP",
            "kind": "pobj",
            "id": 6,
            "head": 0
         },
         {
            "indices": [
               26,
               27
            ],
            "category": "-RRB-",
            "kind": "punct",
            "id": 7,
            "head": 6
         },
         {
            "indices": [
               28,
               30
            ],
            "category": "IN",
            "kind": "prep",
            "id": 8,
            "head": 0
         },
         {
            "indices": [
               31,
               34
            ],
            "category": "NNP",
            "kind": "pobj",
            "id": 9,
            "head": 8
         },
         {
            "indices": [
               34,
               35
            ],
            "category": "NNP",
            "kind": "pobj",
            "id": 10,
            "head": 8
         },
         {
            "indices": [
               36,
               37
            ],
            "category": "CD",
            "kind": "dep",
            "id": 11,
            "head": 12
         },
         {
            "indices": [
               37,
               38
            ],
            "category": ",",
            "kind": "punct",
            "id": 12,
            "head": 17
         },
         {
            "indices": [
               39,
               42
            ],
            "category": "DT",
            "kind": "det",
            "id": 13,
            "head": 16
         },
         {
            "indices": [
               43,
               44
            ],
            "category": "NN",
            "kind": "dep",
            "id": 14,
            "head": 15
         },
         {
            "indices": [
               44,
               45
            ],
            "category": "HYPH",
            "kind": "punct",
            "id": 15,
            "head": 16
         },
         {
            "indices": [
               45,
               55
            ],
            "category": "JJ",
            "kind": "nsubj",
            "id": 16,
            "head": 17
         },
         {
            "indices": [
               56,
               64
            ],
            "category": "NNS",
            "kind": "ROOT",
            "id": 17,
            "head": 17
         },
         {
            "indices": [
               65,
               67
            ],
            "category": "IN",
            "kind": "prep",
            "id": 18,
            "head": 17
         },
         {
            "indices": [
               68,
               71
            ],
            "category": "DT",
            "kind": "det",
            "id": 19,
            "head": 20
         },
         {
            "indices": [
               72,
               77
            ],
            "category": "NN",
            "kind": "pobj",
            "id": 20,
            "head": 18
         },
         {
            "indices": [
               78,
               80
            ],
            "category": "IN",
            "kind": "prep",
            "id": 21,
            "head": 20
         },
         {
            "indices": [
               81,
               84
            ],
            "category": "DT",
            "kind": "det",
            "id": 22,
            "head": 23
         },
         {
            "indices": [
               85,
               91
            ],
            "category": "NN",
            "kind": "pobj",
            "id": 23,
            "head": 21
         },
         {
            "indices": [
               92,
               94
            ],
            "category": "IN",
            "kind": "prep",
            "id": 24,
            "head": 23
         },
         {
            "indices": [
               95,
               98
            ],
            "category": "DT",
            "kind": "det",
            "id": 25,
            "head": 27
         },
         {
            "indices": [
               99,
               107
            ],
            "category": "VBN",
            "kind": "amod",
            "id": 26,
            "head": 27
         },
         {
            "indices": [
               108,
               115
            ],
            "category": "NNS",
            "kind": "pobj",
            "id": 27,
            "head": 24
         },
         {
            "indices": [
               116,
               119
            ],
            "category": "CC",
            "kind": "cc",
            "id": 28,
            "head": 27
         },
         {
            "indices": [
               120,
               128
            ],
            "category": "JJ",
            "kind": "amod",
            "id": 29,
            "head": 30
         },
         {
            "indices": [
               129,
               133
            ],
            "category": "NNS",
            "kind": "conj",
            "id": 30,
            "head": 27
         },
         {
            "indices": [
               133,
               134
            ],
            "category": ",",
            "kind": "punct",
            "id": 31,
            "head": 17
         },
         {
            "indices": [
               135,
               140
            ],
            "category": "IN",
            "kind": "mark",
            "id": 32,
            "head": 37
         },
         {
            "indices": [
               141,
               144
            ],
            "category": "DT",
            "kind": "det",
            "id": 33,
            "head": 37
         },
         {
            "indices": [
               145,
               146
            ],
            "category": "NN",
            "kind": "compound",
            "id": 34,
            "head": 36
         },
         {
            "indices": [
               146,
               147
            ],
            "category": "HYPH",
            "kind": "punct",
            "id": 35,
            "head": 36
         },
         {
            "indices": [
               147,
               157
            ],
            "category": "VB",
            "kind": "amod",
            "id": 36,
            "head": 37
         },
         {
            "indices": [
               158,
               166
            ],
            "category": "NNS",
            "kind": "advcl",
            "id": 37,
            "head": 17
         },
         {
            "indices": [
               167,
               170
            ],
            "category": "DT",
            "kind": "det",
            "id": 38,
            "head": 40
         },
         {
            "indices": [
               171,
               184
            ],
            "category": "JJ",
            "kind": "amod",
            "id": 39,
            "head": 40
         },
         {
            "indices": [
               185,
               189
            ],
            "category": "NN",
            "kind": "npadvmod",
            "id": 40,
            "head": 37
         },
         {
            "indices": [
               189,
               190
            ],
            "category": ".",
            "kind": "punct",
            "id": 41,
            "head": 17
         },
         {
            "indices": [
               191,
               200
            ],
            "category": "VBG",
            "kind": "prep",
            "id": 42,
            "head": 58
         },
         {
            "indices": [
               201,
               203
            ],
            "category": "IN",
            "kind": "prep",
            "id": 43,
            "head": 42
         },
         {
            "indices": [
               204,
               207
            ],
            "category": "DT",
            "kind": "det",
            "id": 44,
            "head": 46
         },
         {
            "indices": [
               208,
               220
            ],
            "category": "JJ",
            "kind": "amod",
            "id": 45,
            "head": 46
         },
         {
            "indices": [
               221,
               228
            ],
            "category": "NNS",
            "kind": "pobj",
            "id": 46,
            "head": 43
         },
         {
            "indices": [
               229,
               231
            ],
            "category": "IN",
            "kind": "mark",
            "id": 47,
            "head": 48
         },
         {
            "indices": [
               232,
               237
            ],
            "category": "VBN",
            "kind": "acl",
            "id": 48,
            "head": 46
         },
         {
            "indices": [
               238,
               240
            ],
            "category": "IN",
            "kind": "prep",
            "id": 49,
            "head": 48
         },
         {
            "indices": [
               241,
               246
            ],
            "category": "NNP",
            "kind": "pobj",
            "id": 50,
            "head": 49
         },
         {
            "indices": [
               247,
               248
            ],
            "category": "CD",
            "kind": "nummod",
            "id": 51,
            "head": 50
         },
         {
            "indices": [
               249,
               252
            ],
            "category": "CC",
            "kind": "cc",
            "id": 52,
            "head": 50
         },
         {
            "indices": [
               253,
               256
            ],
            "category": "NNP",
            "kind": "dep",
            "id": 53,
            "head": 54
         },
         {
            "indices": [
               256,
               257
            ],
            "category": "NNP",
            "kind": "pobj",
            "id": 54,
            "head": 42
         },
         {
            "indices": [
               258,
               259
            ],
            "category": "CD",
            "kind": "dep",
            "id": 55,
            "head": 56
         },
         {
            "indices": [
               259,
               260
            ],
            "category": ",",
            "kind": "punct",
            "id": 56,
            "head": 58
         },
         {
            "indices": [
               261,
               263
            ],
            "category": "PRP",
            "kind": "nsubj",
            "id": 57,
            "head": 58
         },
         {
            "indices": [
               264,
               268
            ],
            "category": "VBP",
            "kind": "ROOT",
            "id": 58,
            "head": 58
         },
         {
            "indices": [
               269,
               273
            ],
            "category": "IN",
            "kind": "mark",
            "id": 59,
            "head": 78
         },
         {
            "indices": [
               274,
               277
            ],
            "category": "DT",
            "kind": "det",
            "id": 60,
            "head": 62
         },
         {
            "indices": [
               278,
               291
            ],
            "category": "JJ",
            "kind": "amod",
            "id": 61,
            "head": 62
         },
         {
            "indices": [
               292,
               296
            ],
            "category": "NN",
            "kind": "nsubj",
            "id": 62,
            "head": 78
         },
         {
            "indices": [
               297,
               299
            ],
            "category": "IN",
            "kind": "prep",
            "id": 63,
            "head": 62
         },
         {
            "indices": [
               300,
               304
            ],
            "category": "DT",
            "kind": "det",
            "id": 64,
            "head": 65
         },
         {
            "indices": [
               305,
               311
            ],
            "category": "JJ",
            "kind": "pobj",
            "id": 65,
            "head": 63
         },
         {
            "indices": [
               312,
               313
            ],
            "category": "-LRB-",
            "kind": "punct",
            "id": 66,
            "head": 67
         },
         {
            "indices": [
               313,
               322
            ],
            "category": "NN",
            "kind": "appos",
            "id": 67,
            "head": 62
         },
         {
            "indices": [
               323,
               324
            ],
            "category": "CD",
            "kind": "nummod",
            "id": 68,
            "head": 67
         },
         {
            "indices": [
               324,
               325
            ],
            "category": "-RRB-",
            "kind": "punct",
            "id": 69,
            "head": 67
         },
         {
            "indices": [
               326,
               329
            ],
            "category": "CC",
            "kind": "cc",
            "id": 70,
            "head": 62
         },
         {
            "indices": [
               330,
               341
            ],
            "category": "JJ",
            "kind": "amod",
            "id": 71,
            "head": 76
         },
         {
            "indices": [
               342,
               343
            ],
            "category": "-LRB-",
            "kind": "punct",
            "id": 72,
            "head": 76
         },
         {
            "indices": [
               343,
               352
            ],
            "category": "NN",
            "kind": "nmod",
            "id": 73,
            "head": 76
         },
         {
            "indices": [
               353,
               354
            ],
            "category": "CD",
            "kind": "nummod",
            "id": 74,
            "head": 73
         },
         {
            "indices": [
               354,
               355
            ],
            "category": "-RRB-",
            "kind": "punct",
            "id": 75,
            "head": 73
         },
         {
            "indices": [
               356,
               366
            ],
            "category": "NNS",
            "kind": "conj",
            "id": 76,
            "head": 62
         },
         {
            "indices": [
               367,
               370
            ],
            "category": "VBP",
            "kind": "aux",
            "id": 77,
            "head": 78
         },
         {
            "indices": [
               371,
               381
            ],
            "category": "VBG",
            "kind": "ccomp",
            "id": 78,
            "head": 58
         },
         {
            "indices": [
               382,
               395
            ],
            "category": "RB",
            "kind": "advmod",
            "id": 79,
            "head": 78
         },
         {
            "indices": [
               396,
               401
            ],
            "category": "IN",
            "kind": "prep",
            "id": 80,
            "head": 78
         },
         {
            "indices": [
               402,
               406
            ],
            "category": "IN",
            "kind": "prep",
            "id": 81,
            "head": 80
         },
         {
            "indices": [
               407,
               410
            ],
            "category": "DT",
            "kind": "det",
            "id": 82,
            "head": 83
         },
         {
            "indices": [
               411,
               421
            ],
            "category": "VBG",
            "kind": "pobj",
            "id": 83,
            "head": 81
         },
         {
            "indices": [
               422,
               424
            ],
            "category": "IN",
            "kind": "prep",
            "id": 84,
            "head": 83
         },
         {
            "indices": [
               425,
               431
            ],
            "category": "JJ",
            "kind": "compound",
            "id": 85,
            "head": 86
         },
         {
            "indices": [
               432,
               438
            ],
            "category": "NNS",
            "kind": "pobj",
            "id": 86,
            "head": 84
         },
         {
            "indices": [
               438,
               439
            ],
            "category": ".",
            "kind": "punct",
            "id": 87,
            "head": 58
         },
         {
            "indices": [
               440,
               442
            ],
            "category": "PRP",
            "kind": "nsubj",
            "id": 88,
            "head": 89
         },
         {
            "indices": [
               443,
               445
            ],
            "category": "VBZ",
            "kind": "ROOT",
            "id": 89,
            "head": 89
         },
         {
            "indices": [
               446,
               450
            ],
            "category": "JJ",
            "kind": "acomp",
            "id": 90,
            "head": 89
         },
         {
            "indices": [
               451,
               453
            ],
            "category": "TO",
            "kind": "aux",
            "id": 91,
            "head": 92
         },
         {
            "indices": [
               454,
               457
            ],
            "category": "VB",
            "kind": "xcomp",
            "id": 92,
            "head": 89
         },
         {
            "indices": [
               458,
               461
            ],
            "category": "DT",
            "kind": "det",
            "id": 93,
            "head": 95
         },
         {
            "indices": [
               462,
               473
            ],
            "category": "JJ",
            "kind": "amod",
            "id": 94,
            "head": 95
         },
         {
            "indices": [
               474,
               483
            ],
            "category": "NN",
            "kind": "nsubj",
            "id": 95,
            "head": 96
         },
         {
            "indices": [
               484,
               486
            ],
            "category": "VBZ",
            "kind": "ccomp",
            "id": 96,
            "head": 92
         },
         {
            "indices": [
               487,
               493
            ],
            "category": "RB",
            "kind": "advmod",
            "id": 97,
            "head": 96
         },
         {
            "indices": [
               494,
               500
            ],
            "category": "JJR",
            "kind": "acomp",
            "id": 98,
            "head": 96
         },
         {
            "indices": [
               501,
               505
            ],
            "category": "IN",
            "kind": "prep",
            "id": 99,
            "head": 98
         },
         {
            "indices": [
               506,
               509
            ],
            "category": "DT",
            "kind": "det",
            "id": 100,
            "head": 102
         },
         {
            "indices": [
               510,
               516
            ],
            "category": "JJ",
            "kind": "amod",
            "id": 101,
            "head": 102
         },
         {
            "indices": [
               517,
               526
            ],
            "category": "NN",
            "kind": "pobj",
            "id": 102,
            "head": 99
         },
         {
            "indices": [
               527,
               531
            ],
            "category": "WRB",
            "kind": "advmod",
            "id": 103,
            "head": 107
         },
         {
            "indices": [
               532,
               535
            ],
            "category": "DT",
            "kind": "det",
            "id": 104,
            "head": 106
         },
         {
            "indices": [
               536,
               545
            ],
            "category": "VBG",
            "kind": "amod",
            "id": 105,
            "head": 106
         },
         {
            "indices": [
               546,
               551
            ],
            "category": "NN",
            "kind": "nsubj",
            "id": 106,
            "head": 107
         },
         {
            "indices": [
               552,
               561
            ],
            "category": "NNS",
            "kind": "advcl",
            "id": 107,
            "head": 96
         },
         {
            "indices": [
               562,
               566
            ],
            "category": "IN",
            "kind": "prep",
            "id": 108,
            "head": 107
         },
         {
            "indices": [
               567,
               569
            ],
            "category": "CD",
            "kind": "nummod",
            "id": 109,
            "head": 110
         },
         {
            "indices": [
               569,
               570
            ],
            "category": "NN",
            "kind": "quantmod",
            "id": 110,
            "head": 112
         },
         {
            "indices": [
               571,
               573
            ],
            "category": "TO",
            "kind": "quantmod",
            "id": 111,
            "head": 112
         },
         {
            "indices": [
               574,
               577
            ],
            "category": "CD",
            "kind": "nummod",
            "id": 112,
            "head": 113
         },
         {
            "indices": [
               577,
               578
            ],
            "category": "NN",
            "kind": "pobj",
            "id": 113,
            "head": 108
         },
         {
            "indices": [
               579,
               588
            ],
            "category": "VBG",
            "kind": "prep",
            "id": 114,
            "head": 107
         },
         {
            "indices": [
               589,
               591
            ],
            "category": "IN",
            "kind": "prep",
            "id": 115,
            "head": 114
         },
         {
            "indices": [
               592,
               595
            ],
            "category": "NNP",
            "kind": "pobj",
            "id": 116,
            "head": 115
         },
         {
            "indices": [
               595,
               596
            ],
            "category": "NNP",
            "kind": "punct",
            "id": 117,
            "head": 89
         },
         {
            "indices": [
               597,
               604
            ],
            "category": "CD",
            "kind": "dep",
            "id": 118,
            "head": 119
         },
         {
            "indices": [
               604,
               605
            ],
            "category": "-RRB-",
            "kind": "punct",
            "id": 119,
            "head": 89
         },
         {
            "indices": [
               605,
               606
            ],
            "category": ".",
            "kind": "punct",
            "id": 120,
            "head": 89
         },
         {
            "indices": [
               607,
               609
            ],
            "category": "IN",
            "kind": "prep",
            "id": 121,
            "head": 128
         },
         {
            "indices": [
               610,
               613
            ],
            "category": "NNP",
            "kind": "pobj",
            "id": 122,
            "head": 121
         },
         {
            "indices": [
               613,
               614
            ],
            "category": ".",
            "kind": "punct",
            "id": 123,
            "head": 121
         },
         {
            "indices": [
               615,
               618
            ],
            "category": "CD",
            "kind": "pobj",
            "id": 124,
            "head": 121
         },
         {
            "indices": [
               618,
               619
            ],
            "category": "-RRB-",
            "kind": "punct",
            "id": 125,
            "head": 124
         },
         {
            "indices": [
               619,
               620
            ],
            "category": ",",
            "kind": "punct",
            "id": 126,
            "head": 128
         },
         {
            "indices": [
               621,
               623
            ],
            "category": "PRP",
            "kind": "nsubj",
            "id": 127,
            "head": 128
         },
         {
            "indices": [
               624,
               628
            ],
            "category": "VBP",
            "kind": "ROOT",
            "id": 128,
            "head": 128
         },
         {
            "indices": [
               629,
               632
            ],
            "category": "DT",
            "kind": "det",
            "id": 129,
            "head": 131
         },
         {
            "indices": [
               633,
               644
            ],
            "category": "JJ",
            "kind": "amod",
            "id": 130,
            "head": 131
         },
         {
            "indices": [
               645,
               654
            ],
            "category": "NN",
            "kind": "nsubj",
            "id": 131,
            "head": 132
         },
         {
            "indices": [
               655,
               657
            ],
            "category": "VBZ",
            "kind": "ccomp",
            "id": 132,
            "head": 128
         },
         {
            "indices": [
               658,
               662
            ],
            "category": "JJ",
            "kind": "dep",
            "id": 133,
            "head": 132
         },
         {
            "indices": [
               663,
               669
            ],
            "category": "RBR",
            "kind": "acomp",
            "id": 134,
            "head": 132
         },
         {
            "indices": [
               670,
               674
            ],
            "category": "IN",
            "kind": "prep",
            "id": 135,
            "head": 134
         },
         {
            "indices": [
               675,
               678
            ],
            "category": "DT",
            "kind": "det",
            "id": 136,
            "head": 138
         },
         {
            "indices": [
               679,
               685
            ],
            "category": "JJ",
            "kind": "amod",
            "id": 137,
            "head": 138
         },
         {
            "indices": [
               686,
               695
            ],
            "category": "NN",
            "kind": "pobj",
            "id": 138,
            "head": 135
         },
         {
            "indices": [
               696,
               700
            ],
            "category": "WRB",
            "kind": "advmod",
            "id": 139,
            "head": 143
         },
         {
            "indices": [
               701,
               704
            ],
            "category": "DT",
            "kind": "det",
            "id": 140,
            "head": 142
         },
         {
            "indices": [
               705,
               714
            ],
            "category": "VBG",
            "kind": "amod",
            "id": 141,
            "head": 142
         },
         {
            "indices": [
               715,
               720
            ],
            "category": "NN",
            "kind": "nsubj",
            "id": 142,
            "head": 143
         },
         {
            "indices": [
               721,
               723
            ],
            "category": "VBZ",
            "kind": "advcl",
            "id": 143,
            "head": 132
         },
         {
            "indices": [
               724,
               728
            ],
            "category": "JJR",
            "kind": "amod",
            "id": 144,
            "head": 146
         },
         {
            "indices": [
               729,
               733
            ],
            "category": "IN",
            "kind": "quantmod",
            "id": 145,
            "head": 146
         },
         {
            "indices": [
               734,
               736
            ],
            "category": "CD",
            "kind": "nummod",
            "id": 146,
            "head": 147
         },
         {
            "indices": [
               736,
               737
            ],
            "category": "NN",
            "kind": "attr",
            "id": 147,
            "head": 143
         },
         {
            "indices": [
               737,
               738
            ],
            "category": ",",
            "kind": "punct",
            "id": 148,
            "head": 143
         },
         {
            "indices": [
               739,
               742
            ],
            "category": "CC",
            "kind": "cc",
            "id": 149,
            "head": 143
         },
         {
            "indices": [
               743,
               749
            ],
            "category": "JJR",
            "kind": "acomp",
            "id": 150,
            "head": 143
         },
         {
            "indices": [
               750,
               754
            ],
            "category": "IN",
            "kind": "prep",
            "id": 151,
            "head": 150
         },
         {
            "indices": [
               755,
               758
            ],
            "category": "DT",
            "kind": "det",
            "id": 152,
            "head": 154
         },
         {
            "indices": [
               759,
               765
            ],
            "category": "JJ",
            "kind": "amod",
            "id": 153,
            "head": 154
         },
         {
            "indices": [
               766,
               775
            ],
            "category": "NN",
            "kind": "pobj",
            "id": 154,
            "head": 151
         },
         {
            "indices": [
               776,
               780
            ],
            "category": "WRB",
            "kind": "advmod",
            "id": 155,
            "head": 159
         },
         {
            "indices": [
               781,
               784
            ],
            "category": "DT",
            "kind": "det",
            "id": 156,
            "head": 158
         },
         {
            "indices": [
               785,
               794
            ],
            "category": "VBG",
            "kind": "amod",
            "id": 157,
            "head": 158
         },
         {
            "indices": [
               795,
               800
            ],
            "category": "NN",
            "kind": "nsubj",
            "id": 158,
            "head": 159
         },
         {
            "indices": [
               801,
               803
            ],
            "category": "VBZ",
            "kind": "advcl",
            "id": 159,
            "head": 150
         },
         {
            "indices": [
               804,
               808
            ],
            "category": "JJR",
            "kind": "amod",
            "id": 160,
            "head": 162
         },
         {
            "indices": [
               809,
               813
            ],
            "category": "IN",
            "kind": "quantmod",
            "id": 161,
            "head": 162
         },
         {
            "indices": [
               814,
               816
            ],
            "category": "CD",
            "kind": "nummod",
            "id": 162,
            "head": 163
         },
         {
            "indices": [
               816,
               817
            ],
            "category": "NN",
            "kind": "attr",
            "id": 163,
            "head": 159
         },
         {
            "indices": [
               817,
               818
            ],
            "category": ".",
            "kind": "punct",
            "id": 164,
            "head": 128
         }
      ],
      "CARDINAL": [
         {
            "indices": [
               36,
               37
            ]
         },
         {
            "indices": [
               258,
               259
            ]
         },
         {
            "indices": [
               323,
               324
            ]
         },
         {
            "indices": [
               353,
               354
            ]
         }
      ],
      "LAW": [
         {
            "indices": [
               241,
               248
            ]
         }
      ],
      "PERCENT": [
         {
            "indices": [
               567,
               578
            ]
         },
         {
            "indices": [
               724,
               737
            ]
         },
         {
            "indices": [
               804,
               817
            ]
         }
      ],
      "ORG": [
         {
            "indices": [
               592,
               595
            ]
         }
      ],
      "PERSON": [
         {
            "indices": [
               610,
               613
            ]
         }
      ],
      "NickDependency": [
         {
            "args": [
               "In",
               "In"
            ],
            "kind": "ROOT",
            "indices": [
               0,
               2
            ]
         },
         {
            "args": [
               "figures",
               "each"
            ],
            "kind": "det",
            "indices": [
               3,
               19
            ]
         },
         {
            "args": [
               "-",
               "sub"
            ],
            "kind": "dep",
            "indices": [
               8,
               12
            ]
         },
         {
            "args": [
               "figures",
               "-"
            ],
            "kind": "dep",
            "indices": [
               11,
               19
            ]
         },
         {
            "args": [
               "In",
               "figures"
            ],
            "kind": "pobj",
            "indices": [
               0,
               19
            ]
         },
         {
            "args": [
               "a)\u2013(f",
               "("
            ],
            "kind": "punct",
            "indices": [
               20,
               26
            ]
         },
         {
            "args": [
               "In",
               "a)\u2013(f"
            ],
            "kind": "pobj",
            "indices": [
               0,
               26
            ]
         },
         {
            "args": [
               "a)\u2013(f",
               ")"
            ],
            "kind": "punct",
            "indices": [
               21,
               27
            ]
         },
         {
            "args": [
               "In",
               "of"
            ],
            "kind": "prep",
            "indices": [
               0,
               30
            ]
         },
         {
            "args": [
               "of",
               "Fig"
            ],
            "kind": "pobj",
            "indices": [
               28,
               34
            ]
         },
         {
            "args": [
               "of",
               "."
            ],
            "kind": "pobj",
            "indices": [
               28,
               35
            ]
         },
         {
            "args": [
               ",",
               "4"
            ],
            "kind": "dep",
            "indices": [
               36,
               38
            ]
         },
         {
            "args": [
               "pertains",
               ","
            ],
            "kind": "punct",
            "indices": [
               37,
               64
            ]
         },
         {
            "args": [
               "coordinate",
               "the"
            ],
            "kind": "det",
            "indices": [
               39,
               55
            ]
         },
         {
            "args": [
               "-",
               "x"
            ],
            "kind": "dep",
            "indices": [
               43,
               45
            ]
         },
         {
            "args": [
               "coordinate",
               "-"
            ],
            "kind": "punct",
            "indices": [
               44,
               55
            ]
         },
         {
            "args": [
               "pertains",
               "coordinate"
            ],
            "kind": "nsubj",
            "indices": [
               45,
               64
            ]
         },
         {
            "args": [
               "pertains",
               "pertains"
            ],
            "kind": "ROOT",
            "indices": [
               56,
               64
            ]
         },
         {
            "args": [
               "pertains",
               "to"
            ],
            "kind": "prep",
            "indices": [
               56,
               67
            ]
         },
         {
            "args": [
               "ratio",
               "the"
            ],
            "kind": "det",
            "indices": [
               68,
               77
            ]
         },
         {
            "args": [
               "to",
               "ratio"
            ],
            "kind": "pobj",
            "indices": [
               65,
               77
            ]
         },
         {
            "args": [
               "ratio",
               "of"
            ],
            "kind": "prep",
            "indices": [
               72,
               80
            ]
         },
         {
            "args": [
               "number",
               "the"
            ],
            "kind": "det",
            "indices": [
               81,
               91
            ]
         },
         {
            "args": [
               "of",
               "number"
            ],
            "kind": "pobj",
            "indices": [
               78,
               91
            ]
         },
         {
            "args": [
               "number",
               "of"
            ],
            "kind": "prep",
            "indices": [
               85,
               94
            ]
         },
         {
            "args": [
               "objects",
               "the"
            ],
            "kind": "det",
            "indices": [
               95,
               115
            ]
         },
         {
            "args": [
               "objects",
               "inserted"
            ],
            "kind": "amod",
            "indices": [
               99,
               115
            ]
         },
         {
            "args": [
               "of",
               "objects"
            ],
            "kind": "pobj",
            "indices": [
               92,
               115
            ]
         },
         {
            "args": [
               "objects",
               "and"
            ],
            "kind": "cc",
            "indices": [
               108,
               119
            ]
         },
         {
            "args": [
               "data",
               "original"
            ],
            "kind": "amod",
            "indices": [
               120,
               133
            ]
         },
         {
            "args": [
               "objects",
               "data"
            ],
            "kind": "conj",
            "indices": [
               108,
               133
            ]
         },
         {
            "args": [
               "pertains",
               ","
            ],
            "kind": "punct",
            "indices": [
               56,
               134
            ]
         },
         {
            "args": [
               "concerns",
               "while"
            ],
            "kind": "mark",
            "indices": [
               135,
               166
            ]
         },
         {
            "args": [
               "concerns",
               "the"
            ],
            "kind": "det",
            "indices": [
               141,
               166
            ]
         },
         {
            "args": [
               "coordinate",
               "y"
            ],
            "kind": "compound",
            "indices": [
               145,
               157
            ]
         },
         {
            "args": [
               "coordinate",
               "-"
            ],
            "kind": "punct",
            "indices": [
               146,
               157
            ]
         },
         {
            "args": [
               "concerns",
               "coordinate"
            ],
            "kind": "amod",
            "indices": [
               147,
               166
            ]
         },
         {
            "args": [
               "pertains",
               "concerns"
            ],
            "kind": "advcl",
            "indices": [
               56,
               166
            ]
         },
         {
            "args": [
               "time",
               "the"
            ],
            "kind": "det",
            "indices": [
               167,
               189
            ]
         },
         {
            "args": [
               "time",
               "computational"
            ],
            "kind": "amod",
            "indices": [
               171,
               189
            ]
         },
         {
            "args": [
               "concerns",
               "time"
            ],
            "kind": "npadvmod",
            "indices": [
               158,
               189
            ]
         },
         {
            "args": [
               "pertains",
               "."
            ],
            "kind": "punct",
            "indices": [
               56,
               190
            ]
         },
         {
            "args": [
               "find",
               "According"
            ],
            "kind": "prep",
            "indices": [
               191,
               268
            ]
         },
         {
            "args": [
               "According",
               "to"
            ],
            "kind": "prep",
            "indices": [
               191,
               203
            ]
         },
         {
            "args": [
               "results",
               "the"
            ],
            "kind": "det",
            "indices": [
               204,
               228
            ]
         },
         {
            "args": [
               "results",
               "experimental"
            ],
            "kind": "amod",
            "indices": [
               208,
               228
            ]
         },
         {
            "args": [
               "to",
               "results"
            ],
            "kind": "pobj",
            "indices": [
               201,
               228
            ]
         },
         {
            "args": [
               "shown",
               "as"
            ],
            "kind": "mark",
            "indices": [
               229,
               237
            ]
         },
         {
            "args": [
               "results",
               "shown"
            ],
            "kind": "acl",
            "indices": [
               221,
               237
            ]
         },
         {
            "args": [
               "shown",
               "in"
            ],
            "kind": "prep",
            "indices": [
               232,
               240
            ]
         },
         {
            "args": [
               "in",
               "Table"
            ],
            "kind": "pobj",
            "indices": [
               238,
               246
            ]
         },
         {
            "args": [
               "Table",
               "9"
            ],
            "kind": "nummod",
            "indices": [
               241,
               248
            ]
         },
         {
            "args": [
               "Table",
               "and"
            ],
            "kind": "cc",
            "indices": [
               241,
               252
            ]
         },
         {
            "args": [
               ".",
               "Fig"
            ],
            "kind": "dep",
            "indices": [
               253,
               257
            ]
         },
         {
            "args": [
               "According",
               "."
            ],
            "kind": "pobj",
            "indices": [
               191,
               257
            ]
         },
         {
            "args": [
               ",",
               "4"
            ],
            "kind": "dep",
            "indices": [
               258,
               260
            ]
         },
         {
            "args": [
               "find",
               ","
            ],
            "kind": "punct",
            "indices": [
               259,
               268
            ]
         },
         {
            "args": [
               "find",
               "we"
            ],
            "kind": "nsubj",
            "indices": [
               261,
               268
            ]
         },
         {
            "args": [
               "find",
               "find"
            ],
            "kind": "ROOT",
            "indices": [
               264,
               268
            ]
         },
         {
            "args": [
               "increasing",
               "that"
            ],
            "kind": "mark",
            "indices": [
               269,
               381
            ]
         },
         {
            "args": [
               "time",
               "the"
            ],
            "kind": "det",
            "indices": [
               274,
               296
            ]
         },
         {
            "args": [
               "time",
               "computational"
            ],
            "kind": "amod",
            "indices": [
               278,
               296
            ]
         },
         {
            "args": [
               "increasing",
               "time"
            ],
            "kind": "nsubj",
            "indices": [
               292,
               381
            ]
         },
         {
            "args": [
               "time",
               "of"
            ],
            "kind": "prep",
            "indices": [
               292,
               299
            ]
         },
         {
            "args": [
               "static",
               "both"
            ],
            "kind": "det",
            "indices": [
               300,
               311
            ]
         },
         {
            "args": [
               "of",
               "static"
            ],
            "kind": "pobj",
            "indices": [
               297,
               311
            ]
         },
         {
            "args": [
               "Algorithm",
               "("
            ],
            "kind": "punct",
            "indices": [
               312,
               322
            ]
         },
         {
            "args": [
               "time",
               "Algorithm"
            ],
            "kind": "appos",
            "indices": [
               292,
               322
            ]
         },
         {
            "args": [
               "Algorithm",
               "1"
            ],
            "kind": "nummod",
            "indices": [
               313,
               324
            ]
         },
         {
            "args": [
               "Algorithm",
               ")"
            ],
            "kind": "punct",
            "indices": [
               313,
               325
            ]
         },
         {
            "args": [
               "time",
               "and"
            ],
            "kind": "cc",
            "indices": [
               292,
               329
            ]
         },
         {
            "args": [
               "algorithms",
               "incremental"
            ],
            "kind": "amod",
            "indices": [
               330,
               366
            ]
         },
         {
            "args": [
               "algorithms",
               "("
            ],
            "kind": "punct",
            "indices": [
               342,
               366
            ]
         },
         {
            "args": [
               "algorithms",
               "Algorithm"
            ],
            "kind": "nmod",
            "indices": [
               343,
               366
            ]
         },
         {
            "args": [
               "Algorithm",
               "3"
            ],
            "kind": "nummod",
            "indices": [
               343,
               354
            ]
         },
         {
            "args": [
               "Algorithm",
               ")"
            ],
            "kind": "punct",
            "indices": [
               343,
               355
            ]
         },
         {
            "args": [
               "time",
               "algorithms"
            ],
            "kind": "conj",
            "indices": [
               292,
               366
            ]
         },
         {
            "args": [
               "increasing",
               "are"
            ],
            "kind": "aux",
            "indices": [
               367,
               381
            ]
         },
         {
            "args": [
               "find",
               "increasing"
            ],
            "kind": "ccomp",
            "indices": [
               264,
               381
            ]
         },
         {
            "args": [
               "increasing",
               "monotonically"
            ],
            "kind": "advmod",
            "indices": [
               371,
               395
            ]
         },
         {
            "args": [
               "increasing",
               "along"
            ],
            "kind": "prep",
            "indices": [
               371,
               401
            ]
         },
         {
            "args": [
               "along",
               "with"
            ],
            "kind": "prep",
            "indices": [
               396,
               406
            ]
         },
         {
            "args": [
               "increasing",
               "the"
            ],
            "kind": "det",
            "indices": [
               407,
               421
            ]
         },
         {
            "args": [
               "with",
               "increasing"
            ],
            "kind": "pobj",
            "indices": [
               402,
               421
            ]
         },
         {
            "args": [
               "increasing",
               "of"
            ],
            "kind": "prep",
            "indices": [
               411,
               424
            ]
         },
         {
            "args": [
               "ratios",
               "insert"
            ],
            "kind": "compound",
            "indices": [
               425,
               438
            ]
         },
         {
            "args": [
               "of",
               "ratios"
            ],
            "kind": "pobj",
            "indices": [
               422,
               438
            ]
         },
         {
            "args": [
               "find",
               "."
            ],
            "kind": "punct",
            "indices": [
               264,
               439
            ]
         },
         {
            "args": [
               "is",
               "It"
            ],
            "kind": "nsubj",
            "indices": [
               440,
               445
            ]
         },
         {
            "args": [
               "is",
               "is"
            ],
            "kind": "ROOT",
            "indices": [
               443,
               445
            ]
         },
         {
            "args": [
               "is",
               "easy"
            ],
            "kind": "acomp",
            "indices": [
               443,
               450
            ]
         },
         {
            "args": [
               "get",
               "to"
            ],
            "kind": "aux",
            "indices": [
               451,
               457
            ]
         },
         {
            "args": [
               "is",
               "get"
            ],
            "kind": "xcomp",
            "indices": [
               443,
               457
            ]
         },
         {
            "args": [
               "algorithm",
               "the"
            ],
            "kind": "det",
            "indices": [
               458,
               483
            ]
         },
         {
            "args": [
               "algorithm",
               "incremental"
            ],
            "kind": "amod",
            "indices": [
               462,
               483
            ]
         },
         {
            "args": [
               "is",
               "algorithm"
            ],
            "kind": "nsubj",
            "indices": [
               474,
               486
            ]
         },
         {
            "args": [
               "get",
               "is"
            ],
            "kind": "ccomp",
            "indices": [
               454,
               486
            ]
         },
         {
            "args": [
               "is",
               "always"
            ],
            "kind": "advmod",
            "indices": [
               484,
               493
            ]
         },
         {
            "args": [
               "is",
               "faster"
            ],
            "kind": "acomp",
            "indices": [
               484,
               500
            ]
         },
         {
            "args": [
               "faster",
               "than"
            ],
            "kind": "prep",
            "indices": [
               494,
               505
            ]
         },
         {
            "args": [
               "algorithm",
               "the"
            ],
            "kind": "det",
            "indices": [
               506,
               526
            ]
         },
         {
            "args": [
               "algorithm",
               "static"
            ],
            "kind": "amod",
            "indices": [
               510,
               526
            ]
         },
         {
            "args": [
               "than",
               "algorithm"
            ],
            "kind": "pobj",
            "indices": [
               501,
               526
            ]
         },
         {
            "args": [
               "increases",
               "when"
            ],
            "kind": "advmod",
            "indices": [
               527,
               561
            ]
         },
         {
            "args": [
               "ratio",
               "the"
            ],
            "kind": "det",
            "indices": [
               532,
               551
            ]
         },
         {
            "args": [
               "ratio",
               "inserting"
            ],
            "kind": "amod",
            "indices": [
               536,
               551
            ]
         },
         {
            "args": [
               "increases",
               "ratio"
            ],
            "kind": "nsubj",
            "indices": [
               546,
               561
            ]
         },
         {
            "args": [
               "is",
               "increases"
            ],
            "kind": "advcl",
            "indices": [
               484,
               561
            ]
         },
         {
            "args": [
               "increases",
               "from"
            ],
            "kind": "prep",
            "indices": [
               552,
               566
            ]
         },
         {
            "args": [
               "%",
               "10"
            ],
            "kind": "nummod",
            "indices": [
               567,
               570
            ]
         },
         {
            "args": [
               "100",
               "%"
            ],
            "kind": "quantmod",
            "indices": [
               569,
               577
            ]
         },
         {
            "args": [
               "100",
               "to"
            ],
            "kind": "quantmod",
            "indices": [
               571,
               577
            ]
         },
         {
            "args": [
               "%",
               "100"
            ],
            "kind": "nummod",
            "indices": [
               574,
               578
            ]
         },
         {
            "args": [
               "from",
               "%"
            ],
            "kind": "pobj",
            "indices": [
               562,
               578
            ]
         },
         {
            "args": [
               "increases",
               "according"
            ],
            "kind": "prep",
            "indices": [
               552,
               588
            ]
         },
         {
            "args": [
               "according",
               "to"
            ],
            "kind": "prep",
            "indices": [
               579,
               591
            ]
         },
         {
            "args": [
               "to",
               "Fig"
            ],
            "kind": "pobj",
            "indices": [
               589,
               595
            ]
         },
         {
            "args": [
               "is",
               "."
            ],
            "kind": "punct",
            "indices": [
               443,
               596
            ]
         },
         {
            "args": [
               ")",
               "4(a)\u2013(e"
            ],
            "kind": "dep",
            "indices": [
               597,
               605
            ]
         },
         {
            "args": [
               "is",
               ")"
            ],
            "kind": "punct",
            "indices": [
               443,
               605
            ]
         },
         {
            "args": [
               "is",
               "."
            ],
            "kind": "punct",
            "indices": [
               443,
               606
            ]
         },
         {
            "args": [
               "find",
               "In"
            ],
            "kind": "prep",
            "indices": [
               607,
               628
            ]
         },
         {
            "args": [
               "In",
               "Fig"
            ],
            "kind": "pobj",
            "indices": [
               607,
               613
            ]
         },
         {
            "args": [
               "In",
               "."
            ],
            "kind": "punct",
            "indices": [
               607,
               614
            ]
         },
         {
            "args": [
               "In",
               "4(f"
            ],
            "kind": "pobj",
            "indices": [
               607,
               618
            ]
         },
         {
            "args": [
               "4(f",
               ")"
            ],
            "kind": "punct",
            "indices": [
               615,
               619
            ]
         },
         {
            "args": [
               "find",
               ","
            ],
            "kind": "punct",
            "indices": [
               619,
               628
            ]
         },
         {
            "args": [
               "find",
               "we"
            ],
            "kind": "nsubj",
            "indices": [
               621,
               628
            ]
         },
         {
            "args": [
               "find",
               "find"
            ],
            "kind": "ROOT",
            "indices": [
               624,
               628
            ]
         },
         {
            "args": [
               "algorithm",
               "the"
            ],
            "kind": "det",
            "indices": [
               629,
               654
            ]
         },
         {
            "args": [
               "algorithm",
               "incremental"
            ],
            "kind": "amod",
            "indices": [
               633,
               654
            ]
         },
         {
            "args": [
               "is",
               "algorithm"
            ],
            "kind": "nsubj",
            "indices": [
               645,
               657
            ]
         },
         {
            "args": [
               "find",
               "is"
            ],
            "kind": "ccomp",
            "indices": [
               624,
               657
            ]
         },
         {
            "args": [
               "is",
               "mush"
            ],
            "kind": "dep",
            "indices": [
               655,
               662
            ]
         },
         {
            "args": [
               "is",
               "faster"
            ],
            "kind": "acomp",
            "indices": [
               655,
               669
            ]
         },
         {
            "args": [
               "faster",
               "than"
            ],
            "kind": "prep",
            "indices": [
               663,
               674
            ]
         },
         {
            "args": [
               "algorithm",
               "the"
            ],
            "kind": "det",
            "indices": [
               675,
               695
            ]
         },
         {
            "args": [
               "algorithm",
               "static"
            ],
            "kind": "amod",
            "indices": [
               679,
               695
            ]
         },
         {
            "args": [
               "than",
               "algorithm"
            ],
            "kind": "pobj",
            "indices": [
               670,
               695
            ]
         },
         {
            "args": [
               "is",
               "when"
            ],
            "kind": "advmod",
            "indices": [
               696,
               723
            ]
         },
         {
            "args": [
               "ratio",
               "the"
            ],
            "kind": "det",
            "indices": [
               701,
               720
            ]
         },
         {
            "args": [
               "ratio",
               "inserting"
            ],
            "kind": "amod",
            "indices": [
               705,
               720
            ]
         },
         {
            "args": [
               "is",
               "ratio"
            ],
            "kind": "nsubj",
            "indices": [
               715,
               723
            ]
         },
         {
            "args": [
               "is",
               "is"
            ],
            "kind": "advcl",
            "indices": [
               655,
               723
            ]
         },
         {
            "args": [
               "85",
               "less"
            ],
            "kind": "amod",
            "indices": [
               724,
               736
            ]
         },
         {
            "args": [
               "85",
               "than"
            ],
            "kind": "quantmod",
            "indices": [
               729,
               736
            ]
         },
         {
            "args": [
               "%",
               "85"
            ],
            "kind": "nummod",
            "indices": [
               734,
               737
            ]
         },
         {
            "args": [
               "is",
               "%"
            ],
            "kind": "attr",
            "indices": [
               721,
               737
            ]
         },
         {
            "args": [
               "is",
               ","
            ],
            "kind": "punct",
            "indices": [
               721,
               738
            ]
         },
         {
            "args": [
               "is",
               "but"
            ],
            "kind": "cc",
            "indices": [
               721,
               742
            ]
         },
         {
            "args": [
               "is",
               "slower"
            ],
            "kind": "acomp",
            "indices": [
               721,
               749
            ]
         },
         {
            "args": [
               "slower",
               "than"
            ],
            "kind": "prep",
            "indices": [
               743,
               754
            ]
         },
         {
            "args": [
               "algorithm",
               "the"
            ],
            "kind": "det",
            "indices": [
               755,
               775
            ]
         },
         {
            "args": [
               "algorithm",
               "static"
            ],
            "kind": "amod",
            "indices": [
               759,
               775
            ]
         },
         {
            "args": [
               "than",
               "algorithm"
            ],
            "kind": "pobj",
            "indices": [
               750,
               775
            ]
         },
         {
            "args": [
               "is",
               "when"
            ],
            "kind": "advmod",
            "indices": [
               776,
               803
            ]
         },
         {
            "args": [
               "ratio",
               "the"
            ],
            "kind": "det",
            "indices": [
               781,
               800
            ]
         },
         {
            "args": [
               "ratio",
               "inserting"
            ],
            "kind": "amod",
            "indices": [
               785,
               800
            ]
         },
         {
            "args": [
               "is",
               "ratio"
            ],
            "kind": "nsubj",
            "indices": [
               795,
               803
            ]
         },
         {
            "args": [
               "slower",
               "is"
            ],
            "kind": "advcl",
            "indices": [
               743,
               803
            ]
         },
         {
            "args": [
               "85",
               "more"
            ],
            "kind": "amod",
            "indices": [
               804,
               816
            ]
         },
         {
            "args": [
               "85",
               "than"
            ],
            "kind": "quantmod",
            "indices": [
               809,
               816
            ]
         },
         {
            "args": [
               "%",
               "85"
            ],
            "kind": "nummod",
            "indices": [
               814,
               817
            ]
         },
         {
            "args": [
               "is",
               "%"
            ],
            "kind": "attr",
            "indices": [
               801,
               817
            ]
         },
         {
            "args": [
               "find",
               "."
            ],
            "kind": "punct",
            "indices": [
               624,
               818
            ]
         }
      ],
      "sentence": [
         {
            "indices": [
               0,
               35
            ]
         },
         {
            "indices": [
               36,
               190
            ]
         },
         {
            "indices": [
               191,
               439
            ]
         },
         {
            "indices": [
               440,
               606
            ]
         },
         {
            "indices": [
               607,
               818
            ]
         }
      ],
      "MEval-Quantity": [
         {
            "indices": [
               562,
               578
            ],
            "annotSet": 1,
            "annotId": "T1-1",
            "text": "from 10% to 100%",
            "other": "{\"mods\": [\"IsRange\"], \"unit\": \"%\"}"
         },
         {
            "indices": [
               724,
               737
            ],
            "annotSet": 2,
            "annotId": "T1-2",
            "text": "less than 85%",
            "other": "{\"mods\": [\"IsRange\"], \"unit\": \"%\"}"
         },
         {
            "indices": [
               804,
               817
            ],
            "annotSet": 3,
            "annotId": "T1-3",
            "text": "more than 85%",
            "other": "{\"mods\": [\"IsRange\"], \"unit\": \"%\"}"
         }
      ],
      "MEval-MeasuredProperty": [
         {
            "indices": [
               552,
               561
            ],
            "annotSet": 1,
            "annotId": "T3-1",
            "text": "increases",
            "other": "{\"HasQuantity\": \"T1-1\"}"
         }
      ],
      "MEval-MeasuredEntity": [
         {
            "indices": [
               536,
               551
            ],
            "annotSet": 1,
            "annotId": "T2-1",
            "text": "inserting ratio",
            "other": "{\"HasProperty\": \"T3-1\"}"
         },
         {
            "indices": [
               705,
               720
            ],
            "annotSet": 2,
            "annotId": "T2-2",
            "text": "inserting ratio",
            "other": "{\"HasQuantity\": \"T1-2\"}"
         },
         {
            "indices": [
               785,
               800
            ],
            "annotSet": 3,
            "annotId": "T2-3",
            "text": "inserting ratio",
            "other": "{\"HasQuantity\": \"T1-3\"}"
         }
      ],
      "h0Number": [
         {
            "indices": [
               36,
               37
            ],
            "text": "4"
         },
         {
            "indices": [
               247,
               248
            ],
            "text": "9"
         },
         {
            "indices": [
               258,
               259
            ],
            "text": "4"
         },
         {
            "indices": [
               323,
               324
            ],
            "text": "1"
         },
         {
            "indices": [
               353,
               354
            ],
            "text": "3"
         },
         {
            "indices": [
               567,
               569
            ],
            "text": "10"
         },
         {
            "indices": [
               569,
               570
            ],
            "text": "%"
         },
         {
            "indices": [
               571,
               573
            ],
            "text": "to"
         },
         {
            "indices": [
               574,
               577
            ],
            "text": "100"
         },
         {
            "indices": [
               577,
               578
            ],
            "text": "%"
         },
         {
            "indices": [
               724,
               728
            ],
            "text": "less"
         },
         {
            "indices": [
               729,
               733
            ],
            "text": "than"
         },
         {
            "indices": [
               734,
               736
            ],
            "text": "85"
         },
         {
            "indices": [
               736,
               737
            ],
            "text": "%"
         },
         {
            "indices": [
               804,
               808
            ],
            "text": "more"
         },
         {
            "indices": [
               809,
               813
            ],
            "text": "than"
         },
         {
            "indices": [
               814,
               816
            ],
            "text": "85"
         },
         {
            "indices": [
               816,
               817
            ],
            "text": "%"
         }
      ],
      "h0Unit": [
         {
            "indices": [
               37,
               38
            ],
            "text": ","
         },
         {
            "indices": [
               241,
               246
            ],
            "text": "Table"
         },
         {
            "indices": [
               259,
               260
            ],
            "text": ","
         },
         {
            "indices": [
               313,
               322
            ],
            "text": "Algorithm"
         },
         {
            "indices": [
               343,
               352
            ],
            "text": "Algorithm"
         },
         {
            "indices": [
               569,
               570
            ],
            "text": "%"
         },
         {
            "indices": [
               574,
               577
            ],
            "text": "100"
         },
         {
            "indices": [
               574,
               577
            ],
            "text": "100"
         },
         {
            "indices": [
               577,
               578
            ],
            "text": "%"
         },
         {
            "indices": [
               562,
               566
            ],
            "text": "from"
         },
         {
            "indices": [
               734,
               736
            ],
            "text": "85"
         },
         {
            "indices": [
               734,
               736
            ],
            "text": "85"
         },
         {
            "indices": [
               736,
               737
            ],
            "text": "%"
         },
         {
            "indices": [
               721,
               723
            ],
            "text": "is"
         },
         {
            "indices": [
               814,
               816
            ],
            "text": "85"
         },
         {
            "indices": [
               814,
               816
            ],
            "text": "85"
         },
         {
            "indices": [
               816,
               817
            ],
            "text": "%"
         },
         {
            "indices": [
               801,
               803
            ],
            "text": "is"
         }
      ],
      "h0MeasuredEntity": [
         {
            "indices": [
               56,
               64
            ],
            "text": "pertains"
         },
         {
            "indices": [
               232,
               237
            ],
            "text": "shown"
         },
         {
            "indices": [
               264,
               268
            ],
            "text": "find"
         },
         {
            "indices": [
               292,
               296
            ],
            "text": "time"
         },
         {
            "indices": [
               356,
               366
            ],
            "text": "algorithms"
         },
         {
            "indices": [
               574,
               577
            ],
            "text": "100"
         },
         {
            "indices": [
               577,
               578
            ],
            "text": "%"
         },
         {
            "indices": [
               577,
               578
            ],
            "text": "%"
         },
         {
            "indices": [
               552,
               561
            ],
            "text": "increases"
         },
         {
            "indices": [
               552,
               561
            ],
            "text": "increases"
         },
         {
            "indices": [
               736,
               737
            ],
            "text": "%"
         },
         {
            "indices": [
               736,
               737
            ],
            "text": "%"
         },
         {
            "indices": [
               721,
               723
            ],
            "text": "is"
         },
         {
            "indices": [
               655,
               657
            ],
            "text": "is"
         },
         {
            "indices": [
               816,
               817
            ],
            "text": "%"
         },
         {
            "indices": [
               816,
               817
            ],
            "text": "%"
         },
         {
            "indices": [
               801,
               803
            ],
            "text": "is"
         },
         {
            "indices": [
               743,
               749
            ],
            "text": "slower"
         }
      ],
      "h0NumberTP": [
         {
            "indices": [
               567,
               569
            ],
            "text": "10"
         },
         {
            "indices": [
               724,
               728
            ],
            "text": "less"
         },
         {
            "indices": [
               804,
               808
            ],
            "text": "more"
         }
      ],
      "h0UnitTP": [
         {
            "indices": [
               569,
               570
            ],
            "text": "%"
         },
         {
            "indices": [
               734,
               736
            ],
            "text": "85"
         },
         {
            "indices": [
               814,
               816
            ],
            "text": "85"
         }
      ]
   }
}